src/reverse_type.py
reverse_type-0.1.1.dist-info/entry_points.txt
reverse_type-0.1.1.dist-info/WHEEL
reverse_type-0.1.1.dist-info/METADATA
reverse_type-0.1.1.dist-info/RECORD
