Metadata-Version: 2.1
Name: reverse-type
Version: 0.1.1
Summary: Embeds argument text in Unicode Right-To-Left and reverses it
License: GPL
Author: Johnny Wezel
Author-email: j@wezel.name
Requires-Python: >=3.9,<4.0
Classifier: License :: Other/Proprietary License
Classifier: Programming Language :: Python :: 3
Classifier: Programming Language :: Python :: 3.9
Classifier: Programming Language :: Python :: 3.10
Classifier: Programming Language :: Python :: 3.11
